arclight/__init__.py
arclight/data/2dasource.zip
arclight/erfherder_cli/__init__.py
arclight/erfherder_cli/main.py
arclight/nwscript_lint/__init__.py
arclight/nwscript_lint/main.py
arclight/nwscriptd/README.md
arclight/nwscriptd/__init__.py
arclight/nwscriptd/cli.py
arclight/nwscriptd/markup.py
arclight/nwscriptd/py.typed
arclight/nwscriptd/server.py
arclight/twodilate/__init__.py
arclight/twodilate/main.py
arclight/twodilate/samples/2dx/actions.2dx
arclight/twodilate/samples/2dx/classes_00.2dx
arclight/twodilate/samples/2dx/classes_01.2dx
arclight/twodilate/samples/2dx/loadscreens_00.2dx
arclight/twodilate/samples/2dx/loadscreens_01.2dx
arclight/twodilate/samples/2dx/polymorph_00.2dx
arclight/twodilate/samples/2dx/spells_00.2dx
arclight/twodilate/samples/actions.2da
arclight/twodilate/samples/classes.2da
arclight/twodilate/samples/loadscreens.2da
arclight/twodilate/samples/polymorph.2da
arclight/twodilate/samples/spells.2da
arclight/utils/__init__.py
arclight/utils/image.py
arclight-0.16.0.dist-info/LICENSE
arclight-0.16.0.dist-info/METADATA
arclight-0.16.0.dist-info/WHEEL
arclight-0.16.0.dist-info/entry_points.txt
arclight-0.16.0.dist-info/RECORD
