Metadata-Version: 2.3
Name: arclight
Version: 0.16.0
Summary: A language server for Bioware's nwscript and more!
Keywords: nwscript,Neverwinter Nights,completion,lsp,language-server-protocol
Author: jmd
Author-email: joshua.m.dean@gmail.com
Requires-Python: >=3.10,<4.0
Classifier: Programming Language :: Python :: 3
Classifier: Programming Language :: Python :: 3.10
Classifier: Programming Language :: Python :: 3.11
Classifier: Programming Language :: Python :: 3.12
Classifier: Programming Language :: Python :: 3.13
Requires-Dist: cattrs (>=23.1.2)
Requires-Dist: docstring-to-markdown (==0.*)
Requires-Dist: lsprotocol (>=2022.0.0a9)
Requires-Dist: openpyxl (>=3.1,<4.0)
Requires-Dist: pillow (>=11.0,<12.0)
Requires-Dist: prettytable (>=3.11,<4.0)
Requires-Dist: pygls (>=1.2.1,<2.0.0)
Requires-Dist: rollnw (>=0.42.dev0)
Project-URL: Homepage, https://github.com/jd28/arclight-py
Project-URL: Repository, https://github.com/jd28/arclight-py
